LICENSE
MANIFEST.in
README.rst
setup.py
rfapi/__init__.py
rfapi/apiclient.py
rfapi/auth.py
rfapi/connectapiclient.py
rfapi/datamodel.py
rfapi/dotindex.py
rfapi/error.py
rfapi/query.py
rfapi/rawapiclient.py
rfapi/util.py
rfapi.egg-info/PKG-INFO
rfapi.egg-info/SOURCES.txt
rfapi.egg-info/dependency_links.txt
rfapi.egg-info/requires.txt
rfapi.egg-info/top_level.txt