Metadata-Version: 1.1
Name: rfapi
Version: 2.4.0
Summary: API access to the Recorded Future API.
Home-page: https://github.com/recordedfuture/rfapi-python
Author: Recorded Future, Inc.
Author-email: ['ess@recordedfuture.com', 'edkrantz@recordedfuture.com']
License: Apache 2
Download-URL: https://github.com/recordedfuture/rfapi-python/tarball/2.4.0
Keywords: API,Recorded Future
Platform: UNKNOWN
Classifier: Development Status :: 6 - Mature
Classifier: License :: OSI Approved :: Apache Software License
Classifier: Programming Language :: Python
Classifier: Topic :: Security
